<?xml version="1.0"?>
<opencv_storage>
<stage8>
  <maxWeakCount>7</maxWeakCount>
  <stageThreshold>-1.1956056356430054e+00</stageThreshold>
  <weakClassifiers>
    <_>
      <internalNodes>
        0 -1 272 -514905426 -347654237 -395262261 -276634426 -75729733
        -934747999 -343867649 -2081</internalNodes>
      <leafValues>
        -6.1321908235549927e-01 5.5493998527526855e-01</leafValues></_>
    <_>
      <internalNodes>
        0 -1 2318 14612317 529713372 -305012737 486064438 264993693
        -1078165318 1233865983 -1075054885</internalNodes>
      <leafValues>
        -6.0510784387588501e-01 4.6704834699630737e-01</leafValues></_>
    <_>
      <internalNodes>
        0 -1 3535 -321367585 528375799 -65537 1065074687 -71630851 -8193
        -4259841 -1155334145</internalNodes>
      <leafValues>
        -4.9964511394500732e-01 5.0959300994873047e-01</leafValues></_>
    <_>
      <internalNodes>
        0 -1 139 -352081948 -921966130 1439083094 -1011957624
        -1075314699 -372374890 -1370717401 -39337916</internalNodes>
      <leafValues>
        -5.7951569557189941e-01 3.9147177338600159e-01</leafValues></_>
    <_>
      <internalNodes>
        0 -1 1707 1372996674 1450576981 -497545176 36705429 -1069339568
        -1155923928 553662394 -1087423845</internalNodes>
      <leafValues>
        -6.4614021778106689e-01 3.5259303450584412e-01</leafValues></_>
    <_>
      <internalNodes>
        0 -1 3493 -1119963816 -1651899980 832133520 1997476862 985801692
        950767757 445594461 -6440726</internalNodes>
      <leafValues>
        -5.8910530805587769e-01 3.7651452422142029e-01</leafValues></_>
    <_>
      <internalNodes>
        0 -1 1777 -1459607568 -1619507144 -283852289 -805710779
        -1198993459 -1092892535 -1197831287 -302168891</internalNodes>
      <leafValues>
        -5.7226192951202393e-01 3.6740693449974060e-01</leafValues></_></weakClassifiers></stage8>
</opencv_storage>
